papis/__init__.py
papis/__main__.py
papis/api.py
papis/arxiv.py
papis/bibtex.py
papis/citations.py
papis/cli.py
papis/config.py
papis/crossref.py
papis/dblp.py
papis/defaults.py
papis/dissemin.py
papis/docmatcher.py
papis/document.py
papis/exceptions.py
papis/filetype.py
papis/format.py
papis/fzf.py
papis/git.py
papis/hayagriva.py
papis/hooks.py
papis/id.py
papis/importer.py
papis/isbn.py
papis/json.py
papis/library.py
papis/logging.py
papis/notes.py
papis/paths.py
papis/pick.py
papis/plugin.py
papis/pubmed.py
papis/py.typed
papis/sphinx_ext.py
papis/strings.py
papis/testing.py
papis/utils.py
papis/yaml.py
papis/zenodo.py
papis/commands/__init__.py
papis/commands/add.py
papis/commands/addto.py
papis/commands/bibtex.py
papis/commands/browse.py
papis/commands/cache.py
papis/commands/citations.py
papis/commands/config.py
papis/commands/default.py
papis/commands/doctor.py
papis/commands/edit.py
papis/commands/exec.py
papis/commands/explore.py
papis/commands/export.py
papis/commands/external.py
papis/commands/git.py
papis/commands/init.py
papis/commands/list.py
papis/commands/merge.py
papis/commands/mv.py
papis/commands/open.py
papis/commands/rename.py
papis/commands/rm.py
papis/commands/run.py
papis/commands/serve.py
papis/commands/tag.py
papis/commands/update.py
papis/database/__init__.py
papis/database/base.py
papis/database/cache.py
papis/database/whoosh.py
papis/downloaders/__init__.py
papis/downloaders/acl.py
papis/downloaders/acm.py
papis/downloaders/acs.py
papis/downloaders/annualreviews.py
papis/downloaders/aps.py
papis/downloaders/base.py
papis/downloaders/citeseerx.py
papis/downloaders/fallback.py
papis/downloaders/frontiersin.py
papis/downloaders/get.py
papis/downloaders/hal.py
papis/downloaders/ieee.py
papis/downloaders/iopscience.py
papis/downloaders/projecteuclid.py
papis/downloaders/sciencedirect.py
papis/downloaders/scitationaip.py
papis/downloaders/springer.py
papis/downloaders/tandfonline.py
papis/downloaders/thesesfr.py
papis/downloaders/usenix.py
papis-0.14.dist-info/METADATA
papis-0.14.dist-info/WHEEL
papis-0.14.dist-info/entry_points.txt
papis-0.14.dist-info/licenses/AUTHORS
papis-0.14.dist-info/licenses/LICENSE
papis-0.14.dist-info/RECORD
