Metadata-Version: 2.3
Name: papis
Version: 0.14
Summary: Powerful and highly extensible command-line based document and bibliography manager
Project-URL: Documentation, https://papis.readthedocs.io
Project-URL: Repository, https://github.com/papis/papis
Author-email: Alejandro Gallo <aamsgallo@gmail.com>
Maintainer-email: Alejandro Gallo <aamsgallo@gmail.com>
License: GPL-3.0
License-File: AUTHORS
License-File: LICENSE
Keywords: biblatex,bibtex,biliography,books,cli,command-line,crossref,datasheets,document,elsevier,ieee,latex,libgen,mathematics,mendeley,papers,physics,pubmed,reference manager,research,science,scihub,tui,zotero
Classifier: Development Status :: 4 - Beta
Classifier: Environment :: Console
Classifier: Intended Audience :: Developers
Classifier: Intended Audience :: Education
Classifier: Intended Audience :: End Users/Desktop
Classifier: Intended Audience :: Science/Research
Classifier: Intended Audience :: System Administrators
Classifier: License :: OSI Approved :: GNU General Public License v3 (GPLv3)
Classifier: Natural Language :: English
Classifier: Operating System :: MacOS
Classifier: Operating System :: Microsoft
Classifier: Operating System :: OS Independent
Classifier: Operating System :: POSIX
Classifier: Operating System :: Unix
Classifier: Programming Language :: Python :: 3 :: Only
Classifier: Programming Language :: Python :: 3.8
Classifier: Programming Language :: Python :: 3.9
Classifier: Programming Language :: Python :: 3.10
Classifier: Programming Language :: Python :: 3.11
Classifier: Programming Language :: Python :: 3.12
Classifier: Programming Language :: Python :: 3.13
Classifier: Topic :: Utilities
Requires-Python: >=3.8
Requires-Dist: arxiv>=1.0.0
Requires-Dist: beautifulsoup4>=4.4.1
Requires-Dist: bibtexparser<2,>=0.6.2
Requires-Dist: click>=7
Requires-Dist: colorama>=0.2
Requires-Dist: dominate
Requires-Dist: filetype>=1.0.1
Requires-Dist: habanero>=0.6
Requires-Dist: isbnlib>=3.9.1
Requires-Dist: lxml>=4.3.5
Requires-Dist: platformdirs>=4.0.0
Requires-Dist: prompt-toolkit>=3.0.5
Requires-Dist: pygments>=2.2
Requires-Dist: pyparsing>=2.2
Requires-Dist: python-doi>=0.1.1
Requires-Dist: python-slugify>=1.2.6
Requires-Dist: pyyaml>=3.12
Requires-Dist: requests>=2.11.1
Requires-Dist: stevedore>=1.30
Provides-Extra: develop
Requires-Dist: flake8; extra == 'develop'
Requires-Dist: flake8-bugbear; extra == 'develop'
Requires-Dist: flake8-pyproject; extra == 'develop'
Requires-Dist: flake8-quotes; extra == 'develop'
Requires-Dist: mypy>=0.7; extra == 'develop'
Requires-Dist: pep8-naming; extra == 'develop'
Requires-Dist: pylint; extra == 'develop'
Requires-Dist: pytest; extra == 'develop'
Requires-Dist: pytest-cov; extra == 'develop'
Requires-Dist: python-coveralls; extra == 'develop'
Requires-Dist: types-beautifulsoup4; extra == 'develop'
Requires-Dist: types-docutils; extra == 'develop'
Requires-Dist: types-pygments; extra == 'develop'
Requires-Dist: types-python-slugify; extra == 'develop'
Requires-Dist: types-pyyaml; extra == 'develop'
Requires-Dist: types-requests; extra == 'develop'
Provides-Extra: docs
Requires-Dist: sphinx-click; extra == 'docs'
Requires-Dist: sphinx-design; extra == 'docs'
Requires-Dist: sphinx-rtd-theme>=1; extra == 'docs'
Requires-Dist: sphinx>=4; extra == 'docs'
Provides-Extra: lsp
Requires-Dist: python-lsp-server; extra == 'lsp'
Provides-Extra: optional
Requires-Dist: chardet>=3.0.2; extra == 'optional'
Requires-Dist: jinja2>=3.0.0; extra == 'optional'
Requires-Dist: markdownify>=0.11.6; extra == 'optional'
Requires-Dist: whoosh>=2.7.4; extra == 'optional'
Provides-Extra: windows
Requires-Dist: pyinstaller; extra == 'windows'
